rita/__init__.py
rita/config.py
rita/engine/__init__.py
rita/engine/translate_rust.py
rita/engine/translate_spacy.py
rita/engine/translate_standalone.py
rita/lexer.py
rita/macros.py
rita/modules/__init__.py
rita/modules/fuzzy.py
rita/modules/names.py
rita/modules/orth.py
rita/modules/pluralize.py
rita/modules/regex.py
rita/modules/tag.py
rita/parser.py
rita/precompile.py
rita/preprocess.py
rita/run.py
rita/shortcuts.py
rita/types.py
rita/utils.py
rita_dsl-0.7.4.dist-info/entry_points.txt
rita_dsl-0.7.4.dist-info/LICENSE
rita_dsl-0.7.4.dist-info/WHEEL
rita_dsl-0.7.4.dist-info/METADATA
rita_dsl-0.7.4.dist-info/RECORD
