Metadata-Version: 2.1
Name: rita-dsl
Version: 0.7.4
Summary: DSL for building language rules
Home-page: https://github.com/zaibacu/rita-dsl
License: MIT
Keywords: nlp,rule-based,dsl,pyproject.toml
Author: Šarūnas Navickas
Author-email: sarunas@navickas.info
Requires-Python: >=3.5,<4.0
Classifier: License :: OSI Approved :: MIT License
Classifier: Programming Language :: Python
Classifier: Programming Language :: Python :: 3
Classifier: Programming Language :: Python :: 3.10
Classifier: Programming Language :: Python :: 3.5
Classifier: Programming Language :: Python :: 3.6
Classifier: Programming Language :: Python :: 3.7
Classifier: Programming Language :: Python :: 3.8
Classifier: Programming Language :: Python :: 3.9
Classifier: Programming Language :: Python :: Implementation :: CPython
Classifier: Programming Language :: Python :: Implementation :: PyPy
Requires-Dist: ply (==3.11)
Project-URL: Documentation, https://rita-dsl.readthedocs.io/en/latest/
Project-URL: Repository, https://github.com/zaibacu/rita-dsl
